[{"RecordInfo":{"ApiVer":"1.6.0.0","DeviceId":"NPC700449H","HostUnixTime":1586449024145,"SessionId":"1586449021206"},"PowerDomainData":[{"Header":{"dataSize":32,"dataType":32,"dataTypeSequence":0,"globalSequence":19,"info":0,"systemTick":720,"timestamp":{"seconds":634555004},"user1":49,"user2":19},"PacketGenTime":1586449030512,"PacketRxUnixTime":1586449030571,"Bands":[3418,2619,0,0,3390,0,0,0],"ExternalValuesMask":0,"FftSize":3,"IsPowerChannelOverrange":false,"SampleRate":1,"ValidDataMask":19},{"Header":{"dataSize":32,"dataType":32,"dataTypeSequence":1,"globalSequence":23,"info":0,"systemTick":1737,"timestamp":{"seconds":634555004},"user1":49,"user2":19},"PacketGenTime":1586449030614,"PacketRxUnixTime":1586449030618,"Bands":[3968,2804,0,0,3548,0,0,0],"ExternalValuesMask":0,"FftSize":3,"IsPowerChannelOverrange":false,"SampleRate":1,"ValidDataMask":19},{"Header":{"dataSize":32,"dataType":32,"dataTypeSequence":2,"globalSequence":27,"info":0,"systemTick":2700,"timestamp":{"seconds":634555004},"user1":49,"user2":19},"PacketGenTime":1586449030710,"PacketRxUnixTime":1586449030735,"Bands":[4289,3057,0,0,3777,0,0,0],"ExternalValuesMask":0,"FftSize":3,"IsPowerChannelOverrange":false,"SampleRate":1,"ValidDataMask":19},{"Header":{"dataSize":32,"dataType":32,"dataTypeSequence":3,"globalSequence":30,"info":0,"systemTick":3745,"timestamp":{"seconds":634555004},"user1":49,"user2":19},"PacketGenTime":1586449030814,"PacketRxUnixTime":1586449030906,"Bands":[4241,3113,0,0,3882,0,0,0],"ExternalValuesMask":0,"FftSize":3,"IsPowerChannelOverrange":false,"SampleRate":1,"ValidDataMask":19},{"Header":{"dataSize":32,"dataType":32,"dataTypeSequence":4,"globalSequence":34,"info":0,"systemTick":4764,"timestamp":{"seconds":634555004},"user1":49,"user2":19},"PacketGenTime":1586449030916,"PacketRxUnixTime":1586449030912,"Bands":[3868,3388,0,0,4085,0,0,0],"ExternalValuesMask":0,"FftSize":3,"IsPowerChannelOverrange":false,"SampleRate":1,"ValidDataMask":19},{"Header":{"dataSize":32,"dataType":32,"dataTypeSequence":5,"globalSequence":38,"info":0,"systemTick":5708,"timestamp":{"seconds":634555004},"user1":49,"user2":19},"PacketGenTime":1586449031011,"PacketRxUnixTime":1586449030993,"Bands":[3219,3551,0,0,4207,0,0,0],"ExternalValuesMask":0,"FftSize":3,"IsPowerChannelOverrange":false,"SampleRate":1,"ValidDataMask":19},{"Header":{"dataSize":32,"dataType":32,"dataTypeSequence":6,"globalSequence":42,"info":0,"systemTick":6731,"timestamp":{"seconds":634555005},"user1":49,"user2":19},"PacketGenTime":1586449031113,"PacketRxUnixTime":1586449031210,"Bands":[2605,3551,0,0,4289,0,0,0],"ExternalValuesMask":0,"FftSize":3,"IsPowerChannelOverrange":false,"SampleRate":1,"ValidDataMask":19},{"Header":{"dataSize":32,"dataType":32,"dataTypeSequence":7,"globalSequence":47,"info":0,"systemTick":7711,"timestamp":{"seconds":634555005},"user1":49,"user2":19},"PacketGenTime":1586449031272,"PacketRxUnixTime":1586449031220,"Bands":[2145,3510,0,0,4404,0,0,0],"ExternalValuesMask":0,"FftSize":3,"IsPowerChannelOverrange":false,"SampleRate":1,"ValidDataMask":19},{"Header":{"dataSize":32,"dataType":32,"dataTypeSequence":8,"globalSequence":50,"info":0,"systemTick":8727,"timestamp":{"seconds":634555005},"user1":49,"user2":19},"PacketGenTime":1586449031374,"PacketRxUnixTime":1586449031276,"Bands":[1735,3522,0,0,4852,0,0,0],"ExternalValuesMask":0,"FftSize":3,"IsPowerChannelOverrange":false,"SampleRate":1,"ValidDataMask":19},{"Header":{"dataSize":32,"dataType":32,"dataTypeSequence":9,"globalSequence":54,"info":0,"systemTick":9779,"timestamp":{"seconds":634555005},"user1":49,"user2":19},"PacketGenTime":1586449031479,"PacketRxUnixTime":1586449031447,"Bands":[1615,3559,0,0,5424,0,0,0],"ExternalValuesMask":0,"FftSize":3,"IsPowerChannelOverrange":false,"SampleRate":1,"ValidDataMask":19},{"Header":{"dataSize":32,"dataType":32,"dataTypeSequence":10,"globalSequence":58,"info":0,"systemTick":10686,"timestamp":{"seconds":634555005},"user1":49,"user2":19},"PacketGenTime":1586449031570,"PacketRxUnixTime":1586449031582,"Bands":[1569,3462,0,0,6319,0,0,0],"ExternalValuesMask":0,"FftSize":3,"IsPowerChannelOverrange":false,"SampleRate":1,"ValidDataMask":19},{"Header":{"dataSize":32,"dataType":32,"dataTypeSequence":11,"globalSequence":62,"info":0,"systemTick":11700,"timestamp":{"seconds":634555005},"user1":49,"user2":19},"PacketGenTime":1586449031671,"PacketRxUnixTime":1586449031631,"Bands":[1655,3336,0,0,6998,0,0,0],"ExternalValuesMask":0,"FftSize":3,"IsPowerChannelOverrange":false,"SampleRate":1,"ValidDataMask":19},{"Header":{"dataSize":32,"dataType":32,"dataTypeSequence":12,"globalSequence":66,"info":0,"systemTick":12695,"timestamp":{"seconds":634555005},"user1":49,"user2":19},"PacketGenTime":1586449031771,"PacketRxUnixTime":1586449031768,"Bands":[1685,3177,0,0,7303,0,0,0],"ExternalValuesMask":0,"FftSize":3,"IsPowerChannelOverrange":false,"SampleRate":1,"ValidDataMask":19},{"Header":{"dataSize":32,"dataType":32,"dataTypeSequence":13,"globalSequence":69,"info":0,"systemTick":13703,"timestamp":{"seconds":634555005},"user1":49,"user2":19},"PacketGenTime":1586449031872,"PacketRxUnixTime":1586449031775,"Bands":[1902,3109,0,0,7566,0,0,0],"ExternalValuesMask":0,"FftSize":3,"IsPowerChannelOverrange":false,"SampleRate":1,"ValidDataMask":19},{"Header":{"dataSize":32,"dataType":32,"dataTypeSequence":14,"globalSequence":73,"info":0,"systemTick":14762,"timestamp":{"seconds":634555005},"user1":49,"user2":19},"PacketGenTime":1586449031978,"PacketRxUnixTime":1586449031945,"Bands":[1749,3039,0,0,7586,0,0,0],"ExternalValuesMask":0,"FftSize":3,"IsPowerChannelOverrange":false,"SampleRate":1,"ValidDataMask":19},{"Header":{"dataSize":32,"dataType":32,"dataTypeSequence":15,"globalSequence":77,"info":0,"systemTick":15772,"timestamp":{"seconds":634555005},"user1":49,"user2":19},"PacketGenTime":1586449032079,"PacketRxUnixTime":1586449032002,"Bands":[1792,2900,0,0,7211,0,0,0],"ExternalValuesMask":0,"FftSize":3,"IsPowerChannelOverrange":false,"SampleRate":1,"ValidDataMask":19},{"Header":{"dataSize":32,"dataType":32,"dataTypeSequence":16,"globalSequence":81,"info":0,"systemTick":16736,"timestamp":{"seconds":634555006},"user1":49,"user2":19},"PacketGenTime":1586449032175,"PacketRxUnixTime":1586449032068,"Bands":[1659,2896,0,0,6773,0,0,0],"ExternalValuesMask":0,"FftSize":3,"IsPowerChannelOverrange":false,"SampleRate":1,"ValidDataMask":19},{"Header":{"dataSize":32,"dataType":32,"dataTypeSequence":17,"globalSequence":87,"info":0,"systemTick":17780,"timestamp":{"seconds":634555006},"user1":49,"user2":19},"PacketGenTime":1586449032193,"PacketRxUnixTime":1586449032290,"Bands":[1595,3101,0,0,6137,0,0,0],"ExternalValuesMask":0,"FftSize":3,"IsPowerChannelOverrange":false,"SampleRate":1,"ValidDataMask":19},{"Header":{"dataSize":32,"dataType":32,"dataTypeSequence":18,"globalSequence":91,"info":0,"systemTick":18852,"timestamp":{"seconds":634555006},"user1":49,"user2":19},"PacketGenTime":1586449032300,"PacketRxUnixTime":1586449032368,"Bands":[1314,3476,0,0,6283,0,0,0],"ExternalValuesMask":0,"FftSize":3,"IsPowerChannelOverrange":false,"SampleRate":1,"ValidDataMask":19},{"Header":{"dataSize":32,"dataType":32,"dataTypeSequence":19,"globalSequence":93,"info":0,"systemTick":19749,"timestamp":{"seconds":634555006},"user1":49,"user2":19},"PacketGenTime":1586449032390,"PacketRxUnixTime":1586449032408,"Bands":[1109,3960,0,0,6805,0,0,0],"ExternalValuesMask":0,"FftSize":3,"IsPowerChannelOverrange":false,"SampleRate":1,"ValidDataMask":19},{"Header":{"dataSize":32,"dataType":32,"dataTypeSequence":20,"globalSequence":97,"info":0,"systemTick":20764,"timestamp":{"seconds":634555006},"user1":49,"user2":19},"PacketGenTime":1586449032491,"PacketRxUnixTime":1586449032477,"Bands":[1019,4779,0,0,7478,0,0,0],"ExternalValuesMask":0,"FftSize":3,"IsPowerChannelOverrange":false,"SampleRate":1,"ValidDataMask":19},{"Header":{"dataSize":32,"dataType":32,"dataTypeSequence":21,"globalSequence":101,"info":0,"systemTick":21713,"timestamp":{"seconds":634555006},"user1":49,"user2":19},"PacketGenTime":1586449032586,"PacketRxUnixTime":1586449032596,"Bands":[1016,5627,0,0,8399,0,0,0],"ExternalValuesMask":0,"FftSize":3,"IsPowerChannelOverrange":false,"SampleRate":1,"ValidDataMask":19},{"Header":{"dataSize":32,"dataType":32,"dataTypeSequence":22,"globalSequence":105,"info":0,"systemTick":22725,"timestamp":{"seconds":634555006},"user1":49,"user2":19},"PacketGenTime":1586449032687,"PacketRxUnixTime":1586449032732,"Bands":[1123,6285,0,0,9793,0,0,0],"ExternalValuesMask":0,"FftSize":3,"IsPowerChannelOverrange":false,"SampleRate":1,"ValidDataMask":19},{"Header":{"dataSize":32,"dataType":32,"dataTypeSequence":23,"globalSequence":109,"info":0,"systemTick":23721,"timestamp":{"seconds":634555006},"user1":49,"user2":19},"PacketGenTime":1586449032787,"PacketRxUnixTime":1586449032837,"Bands":[1312,6769,0,0,10747,0,0,0],"ExternalValuesMask":0,"FftSize":3,"IsPowerChannelOverrange":false,"SampleRate":1,"ValidDataMask":19},{"Header":{"dataSize":32,"dataType":32,"dataTypeSequence":24,"globalSequence":112,"info":0,"systemTick":24732,"timestamp":{"seconds":634555006},"user1":49,"user2":19},"PacketGenTime":1586449032888,"PacketRxUnixTime":1586449032904,"Bands":[1290,7291,0,0,11791,0,0,0],"ExternalValuesMask":0,"FftSize":3,"IsPowerChannelOverrange":false,"SampleRate":1,"ValidDataMask":19},{"Header":{"dataSize":32,"dataType":32,"dataTypeSequence":25,"globalSequence":116,"info":0,"systemTick":25765,"timestamp":{"seconds":634555006},"user1":49,"user2":19},"PacketGenTime":1586449032991,"PacketRxUnixTime":1586449032974,"Bands":[1229,7367,0,0,12184,0,0,0],"ExternalValuesMask":0,"FftSize":3,"IsPowerChannelOverrange":false,"SampleRate":1,"ValidDataMask":19},{"Header":{"dataSize":32,"dataType":32,"dataTypeSequence":26,"globalSequence":120,"info":0,"systemTick":26705,"timestamp":{"seconds":634555007},"user1":49,"user2":19},"PacketGenTime":1586449033085,"PacketRxUnixTime":1586449033077,"Bands":[1175,6880,0,0,12502,0,0,0],"ExternalValuesMask":0,"FftSize":3,"IsPowerChannelOverrange":false,"SampleRate":1,"ValidDataMask":19},{"Header":{"dataSize":32,"dataType":32,"dataTypeSequence":27,"globalSequence":125,"info":0,"systemTick":27713,"timestamp":{"seconds":634555007},"user1":49,"user2":19},"PacketGenTime":1586449033204,"PacketRxUnixTime":1586449033209,"Bands":[1057,5944,0,0,11835,0,0,0],"ExternalValuesMask":0,"FftSize":3,"IsPowerChannelOverrange":false,"SampleRate":1,"ValidDataMask":19},{"Header":{"dataSize":32,"dataType":32,"dataTypeSequence":28,"globalSequence":129,"info":0,"systemTick":28699,"timestamp":{"seconds":634555007},"user1":49,"user2":19},"PacketGenTime":1586449033303,"PacketRxUnixTime":1586449033324,"Bands":[1089,4918,0,0,11076,0,0,0],"ExternalValuesMask":0,"FftSize":3,"IsPowerChannelOverrange":false,"SampleRate":1,"ValidDataMask":19},{"Header":{"dataSize":32,"dataType":32,"dataTypeSequence":29,"globalSequence":134,"info":0,"systemTick":29742,"timestamp":{"seconds":634555007},"user1":49,"user2":19},"PacketGenTime":1586449033407,"PacketRxUnixTime":1586449033436,"Bands":[1037,3968,0,0,10084,0,0,0],"ExternalValuesMask":0,"FftSize":3,"IsPowerChannelOverrange":false,"SampleRate":1,"ValidDataMask":19},{"Header":{"dataSize":32,"dataType":32,"dataTypeSequence":30,"globalSequence":136,"info":0,"systemTick":30773,"timestamp":{"seconds":634555007},"user1":49,"user2":19},"PacketGenTime":1586449033510,"PacketRxUnixTime":1586449033561,"Bands":[1169,3069,0,0,9317,0,0,0],"ExternalValuesMask":0,"FftSize":3,"IsPowerChannelOverrange":false,"SampleRate":1,"ValidDataMask":19},{"Header":{"dataSize":32,"dataType":32,"dataTypeSequence":31,"globalSequence":141,"info":0,"systemTick":31899,"timestamp":{"seconds":634555007},"user1":49,"user2":19},"PacketGenTime":1586449033623,"PacketRxUnixTime":1586449033614,"Bands":[1081,2482,0,0,8420,0,0,0],"ExternalValuesMask":0,"FftSize":3,"IsPowerChannelOverrange":false,"SampleRate":1,"ValidDataMask":19},{"Header":{"dataSize":32,"dataType":32,"dataTypeSequence":32,"globalSequence":144,"info":0,"systemTick":32737,"timestamp":{"seconds":634555007},"user1":49,"user2":19},"PacketGenTime":1586449033707,"PacketRxUnixTime":1586449033812,"Bands":[1193,2318,0,0,7881,0,0,0],"ExternalValuesMask":0,"FftSize":3,"IsPowerChannelOverrange":false,"SampleRate":1,"ValidDataMask":19},{"Header":{"dataSize":32,"dataType":32,"dataTypeSequence":33,"globalSequence":148,"info":0,"systemTick":33684,"timestamp":{"seconds":634555007},"user1":49,"user2":19},"PacketGenTime":1586449033802,"PacketRxUnixTime":1586449033852,"Bands":[1241,2320,0,0,7771,0,0,0],"ExternalValuesMask":0,"FftSize":3,"IsPowerChannelOverrange":false,"SampleRate":1,"ValidDataMask":19},{"Header":{"dataSize":32,"dataType":32,"dataTypeSequence":34,"globalSequence":152,"info":0,"systemTick":34739,"timestamp":{"seconds":634555007},"user1":49,"user2":19},"PacketGenTime":1586449033907,"PacketRxUnixTime":1586449033920,"Bands":[1055,2968,0,0,7906,0,0,0],"ExternalValuesMask":0,"FftSize":3,"IsPowerChannelOverrange":false,"SampleRate":1,"ValidDataMask":19},{"Header":{"dataSize":32,"dataType":32,"dataTypeSequence":35,"globalSequence":155,"info":0,"systemTick":35756,"timestamp":{"seconds":634555007},"user1":49,"user2":19},"PacketGenTime":1586449034009,"PacketRxUnixTime":1586449034037,"Bands":[1131,3635,0,0,7879,0,0,0],"ExternalValuesMask":0,"FftSize":3,"IsPowerChannelOverrange":false,"SampleRate":1,"ValidDataMask":19},{"Header":{"dataSize":32,"dataType":32,"dataTypeSequence":36,"globalSequence":160,"info":0,"systemTick":36700,"timestamp":{"seconds":634555008},"user1":49,"user2":19},"PacketGenTime":1586449034145,"PacketRxUnixTime":1586449034209,"Bands":[1065,4440,0,0,7966,0,0,0],"ExternalValuesMask":0,"FftSize":3,"IsPowerChannelOverrange":false,"SampleRate":1,"ValidDataMask":19},{"Header":{"dataSize":32,"dataType":32,"dataTypeSequence":37,"globalSequence":165,"info":0,"systemTick":37935,"timestamp":{"seconds":634555008},"user1":49,"user2":19},"PacketGenTime":1586449034269,"PacketRxUnixTime":1586449034236,"Bands":[1129,5119,0,0,7775,0,0,0],"ExternalValuesMask":0,"FftSize":3,"IsPowerChannelOverrange":false,"SampleRate":1,"ValidDataMask":19},{"Header":{"dataSize":32,"dataType":32,"dataTypeSequence":38,"globalSequence":168,"info":0,"systemTick":38776,"timestamp":{"seconds":634555008},"user1":49,"user2":19},"PacketGenTime":1586449034353,"PacketRxUnixTime":1586449034276,"Bands":[1326,5524,0,0,7737,0,0,0],"ExternalValuesMask":0,"FftSize":3,"IsPowerChannelOverrange":false,"SampleRate":1,"ValidDataMask":19},{"Header":{"dataSize":32,"dataType":32,"dataTypeSequence":39,"globalSequence":172,"info":0,"systemTick":39723,"timestamp":{"seconds":634555008},"user1":49,"user2":19},"PacketGenTime":1586449034448,"PacketRxUnixTime":1586449034526,"Bands":[1697,5627,0,0,7440,0,0,0],"ExternalValuesMask":0,"FftSize":3,"IsPowerChannelOverrange":false,"SampleRate":1,"ValidDataMask":19},{"Header":{"dataSize":32,"dataType":32,"dataTypeSequence":40,"globalSequence":175,"info":0,"systemTick":40736,"timestamp":{"seconds":634555008},"user1":49,"user2":19},"PacketGenTime":1586449034549,"PacketRxUnixTime":1586449034587,"Bands":[1968,5731,0,0,7287,0,0,0],"ExternalValuesMask":0,"FftSize":3,"IsPowerChannelOverrange":false,"SampleRate":1,"ValidDataMask":19},{"Header":{"dataSize":32,"dataType":32,"dataTypeSequence":41,"globalSequence":179,"info":0,"systemTick":41765,"timestamp":{"seconds":634555008},"user1":49,"user2":19},"PacketGenTime":1586449034652,"PacketRxUnixTime":1586449034594,"Bands":[2281,5809,0,0,7281,0,0,0],"ExternalValuesMask":0,"FftSize":3,"IsPowerChannelOverrange":false,"SampleRate":1,"ValidDataMask":19},{"Header":{"dataSize":32,"dataType":32,"dataTypeSequence":42,"globalSequence":184,"info":0,"systemTick":42920,"timestamp":{"seconds":634555008},"user1":49,"user2":19},"PacketGenTime":1586449034767,"PacketRxUnixTime":1586449034747,"Bands":[2649,5737,0,0,7452,0,0,0],"ExternalValuesMask":0,"FftSize":3,"IsPowerChannelOverrange":false,"SampleRate":1,"ValidDataMask":19},{"Header":{"dataSize":32,"dataType":32,"dataTypeSequence":43,"globalSequence":187,"info":0,"systemTick":43756,"timestamp":{"seconds":634555008},"user1":49,"user2":19},"PacketGenTime":1586449034851,"PacketRxUnixTime":1586449034807,"Bands":[2573,5737,0,0,7488,0,0,0],"ExternalValuesMask":0,"FftSize":3,"IsPowerChannelOverrange":false,"SampleRate":1,"ValidDataMask":19},{"Header":{"dataSize":32,"dataType":32,"dataTypeSequence":44,"globalSequence":191,"info":0,"systemTick":44705,"timestamp":{"seconds":634555008},"user1":49,"user2":19},"PacketGenTime":1586449034946,"PacketRxUnixTime":1586449034938,"Bands":[2655,5984,0,0,7753,0,0,0],"ExternalValuesMask":0,"FftSize":3,"IsPowerChannelOverrange":false,"SampleRate":1,"ValidDataMask":19},{"Header":{"dataSize":32,"dataType":32,"dataTypeSequence":45,"globalSequence":195,"info":0,"systemTick":45709,"timestamp":{"seconds":634555008},"user1":49,"user2":19},"PacketGenTime":1586449035046,"PacketRxUnixTime":1586449034997,"Bands":[2338,5982,0,0,7781,0,0,0],"ExternalValuesMask":0,"FftSize":3,"IsPowerChannelOverrange":false,"SampleRate":1,"ValidDataMask":19},{"Header":{"dataSize":32,"dataType":32,"dataTypeSequence":46,"globalSequence":198,"info":0,"systemTick":46741,"timestamp":{"seconds":634555009},"user1":49,"user2":19},"PacketGenTime":1586449035150,"PacketRxUnixTime":1586449035115,"Bands":[2213,6283,0,0,7857,0,0,0],"ExternalValuesMask":0,"FftSize":3,"IsPowerChannelOverrange":false,"SampleRate":1,"ValidDataMask":19},{"Header":{"dataSize":32,"dataType":32,"dataTypeSequence":47,"globalSequence":203,"info":0,"systemTick":47798,"timestamp":{"seconds":634555009},"user1":49,"user2":19},"PacketGenTime":1586449035234,"PacketRxUnixTime":1586449035180,"Bands":[1858,6215,0,0,7739,0,0,0],"ExternalValuesMask":0,"FftSize":3,"IsPowerChannelOverrange":false,"SampleRate":1,"ValidDataMask":19},{"Header":{"dataSize":32,"dataType":32,"dataTypeSequence":48,"globalSequence":207,"info":0,"systemTick":48740,"timestamp":{"seconds":634555009},"user1":49,"user2":19},"PacketGenTime":1586449035329,"PacketRxUnixTime":1586449035304,"Bands":[1571,5974,0,0,7450,0,0,0],"ExternalValuesMask":0,"FftSize":3,"IsPowerChannelOverrange":false,"SampleRate":1,"ValidDataMask":19},{"Header":{"dataSize":32,"dataType":32,"dataTypeSequence":49,"globalSequence":211,"info":0,"systemTick":49688,"timestamp":{"seconds":634555009},"user1":49,"user2":19},"PacketGenTime":1586449035423,"PacketRxUnixTime":1586449035467,"Bands":[1390,5747,0,0,6711,0,0,0],"ExternalValuesMask":0,"FftSize":3,"IsPowerChannelOverrange":false,"SampleRate":1,"ValidDataMask":19},{"Header":{"dataSize":32,"dataType":32,"dataTypeSequence":50,"globalSequence":215,"info":0,"systemTick":50746,"timestamp":{"seconds":634555009},"user1":49,"user2":19},"PacketGenTime":1586449035529,"PacketRxUnixTime":1586449035531,"Bands":[1278,5452,0,0,5968,0,0,0],"ExternalValuesMask":0,"FftSize":3,"IsPowerChannelOverrange":false,"SampleRate":1,"ValidDataMask":19},{"Header":{"dataSize":32,"dataType":32,"dataTypeSequence":51,"globalSequence":218,"info":0,"systemTick":51760,"timestamp":{"seconds":634555009},"user1":49,"user2":19},"PacketGenTime":1586449035631,"PacketRxUnixTime":1586449035654,"Bands":[1191,4904,0,0,5042,0,0,0],"ExternalValuesMask":0,"FftSize":3,"IsPowerChannelOverrange":false,"SampleRate":1,"ValidDataMask":19},{"Header":{"dataSize":32,"dataType":32,"dataTypeSequence":52,"globalSequence":222,"info":0,"systemTick":52795,"timestamp":{"seconds":634555009},"user1":49,"user2":19},"PacketGenTime":1586449035734,"PacketRxUnixTime":1586449035732,"Bands":[1199,4247,0,0,4040,0,0,0],"ExternalValuesMask":0,"FftSize":3,"IsPowerChannelOverrange":false,"SampleRate":1,"ValidDataMask":19},{"Header":{"dataSize":32,"dataType":32,"dataTypeSequence":53,"globalSequence":226,"info":0,"systemTick":53719,"timestamp":{"seconds":634555009},"user1":49,"user2":19},"PacketGenTime":1586449035826,"PacketRxUnixTime":1586449035780,"Bands":[1149,3862,0,0,3187,0,0,0],"ExternalValuesMask":0,"FftSize":3,"IsPowerChannelOverrange":false,"SampleRate":1,"ValidDataMask":19},{"Header":{"dataSize":32,"dataType":32,"dataTypeSequence":54,"globalSequence":230,"info":0,"systemTick":54738,"timestamp":{"seconds":634555009},"user1":49,"user2":19},"PacketGenTime":1586449035928,"PacketRxUnixTime":1586449035972,"Bands":[1157,3506,0,0,2486,0,0,0],"ExternalValuesMask":0,"FftSize":3,"IsPowerChannelOverrange":false,"SampleRate":1,"ValidDataMask":19},{"Header":{"dataSize":32,"dataType":32,"dataTypeSequence":55,"globalSequence":234,"info":0,"systemTick":55727,"timestamp":{"seconds":634555009},"user1":49,"user2":19},"PacketGenTime":1586449036027,"PacketRxUnixTime":1586449036029,"Bands":[1213,3287,0,0,1836,0,0,0],"ExternalValuesMask":0,"FftSize":3,"IsPowerChannelOverrange":false,"SampleRate":1,"ValidDataMask":19},{"Header":{"dataSize":32,"dataType":32,"dataTypeSequence":56,"globalSequence":237,"info":0,"systemTick":56726,"timestamp":{"seconds":634555010},"user1":49,"user2":19},"PacketGenTime":1586449036127,"PacketRxUnixTime":1586449036131,"Bands":[1259,3302,0,0,1378,0,0,0],"ExternalValuesMask":0,"FftSize":3,"IsPowerChannelOverrange":false,"SampleRate":1,"ValidDataMask":19},{"Header":{"dataSize":32,"dataType":32,"dataTypeSequence":57,"globalSequence":242,"info":0,"systemTick":57801,"timestamp":{"seconds":634555010},"user1":49,"user2":19},"PacketGenTime":1586449036216,"PacketRxUnixTime":1586449036211,"Bands":[1298,3442,0,0,1013,0,0,0],"ExternalValuesMask":0,"FftSize":3,"IsPowerChannelOverrange":false,"SampleRate":1,"ValidDataMask":19},{"Header":{"dataSize":32,"dataType":32,"dataTypeSequence":58,"globalSequence":247,"info":0,"systemTick":58920,"timestamp":{"seconds":634555010},"user1":49,"user2":19},"PacketGenTime":1586449036328,"PacketRxUnixTime":1586449036377,"Bands":[1410,3406,0,0,858,0,0,0],"ExternalValuesMask":0,"FftSize":3,"IsPowerChannelOverrange":false,"SampleRate":1,"ValidDataMask":19},{"Header":{"dataSize":32,"dataType":32,"dataTypeSequence":59,"globalSequence":250,"info":0,"systemTick":59761,"timestamp":{"seconds":634555010},"user1":49,"user2":19},"PacketGenTime":1586449036412,"PacketRxUnixTime":1586449036378,"Bands":[1358,3548,0,0,852,0,0,0],"ExternalValuesMask":0,"FftSize":3,"IsPowerChannelOverrange":false,"SampleRate":1,"ValidDataMask":19},{"Header":{"dataSize":32,"dataType":32,"dataTypeSequence":60,"globalSequence":254,"info":0,"systemTick":60713,"timestamp":{"seconds":634555010},"user1":49,"user2":19},"PacketGenTime":1586449036507,"PacketRxUnixTime":1586449036564,"Bands":[1263,3378,0,0,1219,0,0,0],"ExternalValuesMask":0,"FftSize":3,"IsPowerChannelOverrange":false,"SampleRate":1,"ValidDataMask":19},{"Header":{"dataSize":32,"dataType":32,"dataTypeSequence":61,"globalSequence":2,"info":0,"systemTick":61766,"timestamp":{"seconds":634555010},"user1":49,"user2":19},"PacketGenTime":1586449036613,"PacketRxUnixTime":1586449036626,"Bands":[1149,3442,0,0,1681,0,0,0],"ExternalValuesMask":0,"FftSize":3,"IsPowerChannelOverrange":false,"SampleRate":1,"ValidDataMask":19},{"Header":{"dataSize":32,"dataType":32,"dataTypeSequence":62,"globalSequence":5,"info":0,"systemTick":62769,"timestamp":{"seconds":634555010},"user1":49,"user2":19},"PacketGenTime":1586449036713,"PacketRxUnixTime":1586449036755,"Bands":[894,3227,0,0,2452,0,0,0],"ExternalValuesMask":0,"FftSize":3,"IsPowerChannelOverrange":false,"SampleRate":1,"ValidDataMask":19},{"Header":{"dataSize":32,"dataType":32,"dataTypeSequence":63,"globalSequence":9,"info":0,"systemTick":63687,"timestamp":{"seconds":634555010},"user1":49,"user2":19},"PacketGenTime":1586449036805,"PacketRxUnixTime":1586449036792,"Bands":[808,2834,0,0,3159,0,0,0],"ExternalValuesMask":0,"FftSize":3,"IsPowerChannelOverrange":false,"SampleRate":1,"ValidDataMask":19},{"Header":{"dataSize":32,"dataType":32,"dataTypeSequence":64,"globalSequence":13,"info":0,"systemTick":64707,"timestamp":{"seconds":634555010},"user1":49,"user2":19},"PacketGenTime":1586449036907,"PacketRxUnixTime":1586449036986,"Bands":[683,2691,0,0,3882,0,0,0],"ExternalValuesMask":0,"FftSize":3,"IsPowerChannelOverrange":false,"SampleRate":1,"ValidDataMask":19},{"Header":{"dataSize":32,"dataType":32,"dataTypeSequence":65,"globalSequence":17,"info":0,"systemTick":261,"timestamp":{"seconds":634555010},"user1":49,"user2":19},"PacketGenTime":1586449037016,"PacketRxUnixTime":1586449037047,"Bands":[655,2492,0,0,4566,0,0,0],"ExternalValuesMask":0,"FftSize":3,"IsPowerChannelOverrange":false,"SampleRate":1,"ValidDataMask":19},{"Header":{"dataSize":32,"dataType":32,"dataTypeSequence":66,"globalSequence":21,"info":0,"systemTick":1228,"timestamp":{"seconds":634555011},"user1":49,"user2":19},"PacketGenTime":1586449037112,"PacketRxUnixTime":1586449037157,"Bands":[679,2235,0,0,4817,0,0,0],"ExternalValuesMask":0,"FftSize":3,"IsPowerChannelOverrange":false,"SampleRate":1,"ValidDataMask":19},{"Header":{"dataSize":32,"dataType":32,"dataTypeSequence":67,"globalSequence":25,"info":0,"systemTick":2231,"timestamp":{"seconds":634555011},"user1":49,"user2":19},"PacketGenTime":1586449037222,"PacketRxUnixTime":1586449037217,"Bands":[709,2267,0,0,5111,0,0,0],"ExternalValuesMask":0,"FftSize":3,"IsPowerChannelOverrange":false,"SampleRate":1,"ValidDataMask":19},{"Header":{"dataSize":32,"dataType":32,"dataTypeSequence":68,"globalSequence":29,"info":0,"systemTick":3235,"timestamp":{"seconds":634555011},"user1":49,"user2":19},"PacketGenTime":1586449037322,"PacketRxUnixTime":1586449037282,"Bands":[898,2211,0,0,5329,0,0,0],"ExternalValuesMask":0,"FftSize":3,"IsPowerChannelOverrange":false,"SampleRate":1,"ValidDataMask":19},{"Header":{"dataSize":32,"dataType":32,"dataTypeSequence":69,"globalSequence":33,"info":0,"systemTick":4190,"timestamp":{"seconds":634555011},"user1":49,"user2":19},"PacketGenTime":1586449037418,"PacketRxUnixTime":1586449037447,"Bands":[966,2354,0,0,5755,0,0,0],"ExternalValuesMask":0,"FftSize":3,"IsPowerChannelOverrange":false,"SampleRate":1,"ValidDataMask":19},{"Header":{"dataSize":32,"dataType":32,"dataTypeSequence":70,"globalSequence":37,"info":0,"systemTick":5206,"timestamp":{"seconds":634555011},"user1":49,"user2":19},"PacketGenTime":1586449037519,"PacketRxUnixTime":1586449037567,"Bands":[1077,2382,0,0,6723,0,0,0],"ExternalValuesMask":0,"FftSize":3,"IsPowerChannelOverrange":false,"SampleRate":1,"ValidDataMask":19},{"Header":{"dataSize":32,"dataType":32,"dataTypeSequence":71,"globalSequence":41,"info":0,"systemTick":6196,"timestamp":{"seconds":634555011},"user1":49,"user2":19},"PacketGenTime":1586449037618,"PacketRxUnixTime":1586449037630,"Bands":[1219,2508,0,0,7968,0,0,0],"ExternalValuesMask":0,"FftSize":3,"IsPowerChannelOverrange":false,"SampleRate":1,"ValidDataMask":19},{"Header":{"dataSize":32,"dataType":32,"dataTypeSequence":72,"globalSequence":46,"info":0,"systemTick":7207,"timestamp":{"seconds":634555011},"user1":49,"user2":19},"PacketGenTime":1586449037720,"PacketRxUnixTime":1586449037759,"Bands":[1292,2785,0,0,9630,0,0,0],"ExternalValuesMask":0,"FftSize":3,"IsPowerChannelOverrange":false,"SampleRate":1,"ValidDataMask":19},{"Header":{"dataSize":32,"dataType":32,"dataTypeSequence":73,"globalSequence":48,"info":0,"systemTick":8265,"timestamp":{"seconds":634555011},"user1":49,"user2":19},"PacketGenTime":1586449037825,"PacketRxUnixTime":1586449037815,"Bands":[1400,3032,0,0,10680,0,0,0],"ExternalValuesMask":0,"FftSize":3,"IsPowerChannelOverrange":false,"SampleRate":1,"ValidDataMask":19},{"Header":{"dataSize":32,"dataType":32,"dataTypeSequence":74,"globalSequence":53,"info":0,"systemTick":9387,"timestamp":{"seconds":634555011},"user1":49,"user2":19},"PacketGenTime":1586449037938,"PacketRxUnixTime":1586449037950,"Bands":[1422,3557,0,0,11194,0,0,0],"ExternalValuesMask":0,"FftSize":3,"IsPowerChannelOverrange":false,"SampleRate":1,"ValidDataMask":19},{"Header":{"dataSize":32,"dataType":32,"dataTypeSequence":75,"globalSequence":56,"info":0,"systemTick":10234,"timestamp":{"seconds":634555011},"user1":49,"user2":19},"PacketGenTime":1586449038022,"PacketRxUnixTime":1586449038057,"Bands":[1709,4207,0,0,11472,0,0,0],"ExternalValuesMask":0,"FftSize":3,"IsPowerChannelOverrange":false,"SampleRate":1,"ValidDataMask":19},{"Header":{"dataSize":32,"dataType":32,"dataTypeSequence":76,"globalSequence":60,"info":0,"systemTick":11195,"timestamp":{"seconds":634555012},"user1":49,"user2":19},"PacketGenTime":1586449038118,"PacketRxUnixTime":1586449038180,"Bands":[1952,4986,0,0,10907,0,0,0],"ExternalValuesMask":0,"FftSize":3,"IsPowerChannelOverrange":false,"SampleRate":1,"ValidDataMask":19},{"Header":{"dataSize":32,"dataType":32,"dataTypeSequence":77,"globalSequence":65,"info":0,"systemTick":12238,"timestamp":{"seconds":634555012},"user1":49,"user2":19},"PacketGenTime":1586449038249,"PacketRxUnixTime":1586449038298,"Bands":[2141,5339,0,0,9749,0,0,0],"ExternalValuesMask":0,"FftSize":3,"IsPowerChannelOverrange":false,"SampleRate":1,"ValidDataMask":19},{"Header":{"dataSize":32,"dataType":32,"dataTypeSequence":78,"globalSequence":68,"info":0,"systemTick":13233,"timestamp":{"seconds":634555012},"user1":49,"user2":19},"PacketGenTime":1586449038348,"PacketRxUnixTime":1586449038366,"Bands":[2334,5667,0,0,8500,0,0,0],"ExternalValuesMask":0,"FftSize":3,"IsPowerChannelOverrange":false,"SampleRate":1,"ValidDataMask":19},{"Header":{"dataSize":32,"dataType":32,"dataTypeSequence":79,"globalSequence":72,"info":0,"systemTick":14155,"timestamp":{"seconds":634555012},"user1":49,"user2":19},"PacketGenTime":1586449038440,"PacketRxUnixTime":1586449038410,"Bands":[2468,5795,0,0,6886,0,0,0],"ExternalValuesMask":0,"FftSize":3,"IsPowerChannelOverrange":false,"SampleRate":1,"ValidDataMask":19},{"Header":{"dataSize":32,"dataType":32,"dataTypeSequence":80,"globalSequence":76,"info":0,"systemTick":15178,"timestamp":{"seconds":634555012},"user1":49,"user2":19},"PacketGenTime":1586449038543,"PacketRxUnixTime":1586449038594,"Bands":[2540,5719,0,0,5460,0,0,0],"ExternalValuesMask":0,"FftSize":3,"IsPowerChannelOverrange":false,"SampleRate":1,"ValidDataMask":19},{"Header":{"dataSize":32,"dataType":32,"dataTypeSequence":81,"globalSequence":80,"info":0,"systemTick":16259,"timestamp":{"seconds":634555012},"user1":49,"user2":19},"PacketGenTime":1586449038651,"PacketRxUnixTime":1586449038599,"Bands":[2573,4994,0,0,4500,0,0,0],"ExternalValuesMask":0,"FftSize":3,"IsPowerChannelOverrange":false,"SampleRate":1,"ValidDataMask":19},{"Header":{"dataSize":32,"dataType":32,"dataTypeSequence":82,"globalSequence":84,"info":0,"systemTick":17219,"timestamp":{"seconds":634555012},"user1":49,"user2":19},"PacketGenTime":1586449038747,"PacketRxUnixTime":1586449038722,"Bands":[2512,4336,0,0,3492,0,0,0],"ExternalValuesMask":0,"FftSize":3,"IsPowerChannelOverrange":false,"SampleRate":1,"ValidDataMask":19},{"Header":{"dataSize":32,"dataType":32,"dataTypeSequence":83,"globalSequence":87,"info":0,"systemTick":18208,"timestamp":{"seconds":634555012},"user1":49,"user2":19},"PacketGenTime":1586449038846,"PacketRxUnixTime":1586449038774,"Bands":[2209,3585,0,0,2659,0,0,0],"ExternalValuesMask":0,"FftSize":3,"IsPowerChannelOverrange":false,"SampleRate":1,"ValidDataMask":19},{"Header":{"dataSize":32,"dataType":32,"dataTypeSequence":84,"globalSequence":92,"info":0,"systemTick":19366,"timestamp":{"seconds":634555012},"user1":49,"user2":19},"PacketGenTime":1586449038961,"PacketRxUnixTime":1586449038915,"Bands":[1826,3065,0,0,2267,0,0,0],"ExternalValuesMask":0,"FftSize":3,"IsPowerChannelOverrange":false,"SampleRate":1,"ValidDataMask":19},{"Header":{"dataSize":32,"dataType":32,"dataTypeSequence":85,"globalSequence":95,"info":0,"systemTick":20196,"timestamp":{"seconds":634555012},"user1":49,"user2":19},"PacketGenTime":1586449039044,"PacketRxUnixTime":1586449039020,"Bands":[1551,2826,0,0,1942,0,0,0],"ExternalValuesMask":0,"FftSize":3,"IsPowerChannelOverrange":false,"SampleRate":1,"ValidDataMask":19},{"Header":{"dataSize":32,"dataType":32,"dataTypeSequence":86,"globalSequence":99,"info":0,"systemTick":21223,"timestamp":{"seconds":634555013},"user1":49,"user2":19},"PacketGenTime":1586449039147,"PacketRxUnixTime":1586449039134,"Bands":[1265,2942,0,0,2024,0,0,0],"ExternalValuesMask":0,"FftSize":3,"IsPowerChannelOverrange":false,"SampleRate":1,"ValidDataMask":19},{"Header":{"dataSize":32,"dataType":32,"dataTypeSequence":87,"globalSequence":104,"info":0,"systemTick":22202,"timestamp":{"seconds":634555013},"user1":49,"user2":19},"PacketGenTime":1586449039197,"PacketRxUnixTime":1586449039314,"Bands":[1043,3215,0,0,2468,0,0,0],"ExternalValuesMask":0,"FftSize":3,"IsPowerChannelOverrange":false,"SampleRate":1,"ValidDataMask":19},{"Header":{"dataSize":32,"dataType":32,"dataTypeSequence":88,"globalSequence":108,"info":0,"systemTick":23258,"timestamp":{"seconds":634555013},"user1":49,"user2":19},"PacketGenTime":1586449039302,"PacketRxUnixTime":1586449039321,"Bands":[962,3661,0,0,3289,0,0,0],"ExternalValuesMask":0,"FftSize":3,"IsPowerChannelOverrange":false,"SampleRate":1,"ValidDataMask":19},{"Header":{"dataSize":32,"dataType":32,"dataTypeSequence":89,"globalSequence":111,"info":0,"systemTick":24233,"timestamp":{"seconds":634555013},"user1":49,"user2":19},"PacketGenTime":1586449039400,"PacketRxUnixTime":1586449039485,"Bands":[1039,4145,0,0,5119,0,0,0],"ExternalValuesMask":0,"FftSize":3,"IsPowerChannelOverrange":false,"SampleRate":1,"ValidDataMask":19},{"Header":{"dataSize":32,"dataType":32,"dataTypeSequence":90,"globalSequence":116,"info":0,"systemTick":25390,"timestamp":{"seconds":634555013},"user1":49,"user2":19},"PacketGenTime":1586449039515,"PacketRxUnixTime":1586449039561,"Bands":[1167,4504,0,0,7428,0,0,0],"ExternalValuesMask":0,"FftSize":3,"IsPowerChannelOverrange":false,"SampleRate":1,"ValidDataMask":19},{"Header":{"dataSize":32,"dataType":32,"dataTypeSequence":91,"globalSequence":119,"info":0,"systemTick":26235,"timestamp":{"seconds":634555013},"user1":49,"user2":19},"PacketGenTime":1586449039600,"PacketRxUnixTime":1586449039685,"Bands":[1197,4759,0,0,10377,0,0,0],"ExternalValuesMask":0,"FftSize":3,"IsPowerChannelOverrange":false,"SampleRate":1,"ValidDataMask":19},{"Header":{"dataSize":32,"dataType":32,"dataTypeSequence":92,"globalSequence":123,"info":0,"systemTick":27186,"timestamp":{"seconds":634555013},"user1":49,"user2":19},"PacketGenTime":1586449039695,"PacketRxUnixTime":1586449039742,"Bands":[1312,4687,0,0,13590,0,0,0],"ExternalValuesMask":0,"FftSize":3,"IsPowerChannelOverrange":false,"SampleRate":1,"ValidDataMask":19},{"Header":{"dataSize":32,"dataType":32,"dataTypeSequence":93,"globalSequence":127,"info":0,"systemTick":28242,"timestamp":{"seconds":634555013},"user1":49,"user2":19},"PacketGenTime":1586449039801,"PacketRxUnixTime":1586449039848,"Bands":[1199,4637,0,0,16658,0,0,0],"ExternalValuesMask":0,"FftSize":3,"IsPowerChannelOverrange":false,"SampleRate":1,"ValidDataMask":19},{"Header":{"dataSize":32,"dataType":32,"dataTypeSequence":94,"globalSequence":130,"info":0,"systemTick":29235,"timestamp":{"seconds":634555013},"user1":49,"user2":19},"PacketGenTime":1586449039900,"PacketRxUnixTime":1586449039873,"Bands":[1139,4311,0,0,18702,0,0,0],"ExternalValuesMask":0,"FftSize":3,"IsPowerChannelOverrange":false,"SampleRate":1,"ValidDataMask":19},{"Header":{"dataSize":32,"dataType":32,"dataTypeSequence":95,"globalSequence":134,"info":0,"systemTick":30160,"timestamp":{"seconds":634555013},"user1":49,"user2":19},"PacketGenTime":1586449039992,"PacketRxUnixTime":1586449040055,"Bands":[986,3685,0,0,19411,0,0,0],"ExternalValuesMask":0,"FftSize":3,"IsPowerChannelOverrange":false,"SampleRate":1,"ValidDataMask":19},{"Header":{"dataSize":32,"dataType":32,"dataTypeSequence":96,"globalSequence":138,"info":0,"systemTick":31189,"timestamp":{"seconds":634555014},"user1":49,"user2":19},"PacketGenTime":1586449040095,"PacketRxUnixTime":1586449040155,"Bands":[1051,3101,0,0,19507,0,0,0],"ExternalValuesMask":0,"FftSize":3,"IsPowerChannelOverrange":false,"SampleRate":1,"ValidDataMask":19},{"Header":{"dataSize":32,"dataType":32,"dataTypeSequence":97,"globalSequence":143,"info":0,"systemTick":32259,"timestamp":{"seconds":634555014},"user1":49,"user2":19},"PacketGenTime":1586449040226,"PacketRxUnixTime":1586449040228,"Bands":[1396,2751,0,0,17742,0,0,0],"ExternalValuesMask":0,"FftSize":3,"IsPowerChannelOverrange":false,"SampleRate":1,"ValidDataMask":19},{"Header":{"dataSize":32,"dataType":32,"dataTypeSequence":98,"globalSequence":147,"info":0,"systemTick":33224,"timestamp":{"seconds":634555014},"user1":49,"user2":19},"PacketGenTime":1586449040323,"PacketRxUnixTime":1586449040404,"Bands":[2322,2328,0,0,15238,0,0,0],"ExternalValuesMask":0,"FftSize":3,"IsPowerChannelOverrange":false,"SampleRate":1,"ValidDataMask":19},{"Header":{"dataSize":32,"dataType":32,"dataTypeSequence":99,"globalSequence":152,"info":0,"systemTick":34392,"timestamp":{"seconds":634555014},"user1":49,"user2":19},"PacketGenTime":1586449040440,"PacketRxUnixTime":1586449040474,"Bands":[3954,2161,0,0,12204,0,0,0],"ExternalValuesMask":0,"FftSize":3,"IsPowerChannelOverrange":false,"SampleRate":1,"ValidDataMask":19},{"Header":{"dataSize":32,"dataType":32,"dataTypeSequence":100,"globalSequence":155,"info":0,"systemTick":35390,"timestamp":{"seconds":634555014},"user1":49,"user2":19},"PacketGenTime":1586449040540,"PacketRxUnixTime":1586449040530,"Bands":[6125,2320,0,0,9769,0,0,0],"ExternalValuesMask":0,"FftSize":3,"IsPowerChannelOverrange":false,"SampleRate":1,"ValidDataMask":19},{"Header":{"dataSize":32,"dataType":32,"dataTypeSequence":101,"globalSequence":158,"info":0,"systemTick":36201,"timestamp":{"seconds":634555014},"user1":49,"user2":19},"PacketGenTime":1586449040621,"PacketRxUnixTime":1586449040594,"Bands":[8996,2860,0,0,7643,0,0,0],"ExternalValuesMask":0,"FftSize":3,"IsPowerChannelOverrange":false,"SampleRate":1,"ValidDataMask":19},{"Header":{"dataSize":32,"dataType":32,"dataTypeSequence":102,"globalSequence":162,"info":0,"systemTick":37216,"timestamp":{"seconds":634555014},"user1":49,"user2":19},"PacketGenTime":1586449040722,"PacketRxUnixTime":1586449040748,"Bands":[11775,3834,0,0,6590,0,0,0],"ExternalValuesMask":0,"FftSize":3,"IsPowerChannelOverrange":false,"SampleRate":1,"ValidDataMask":19},{"Header":{"dataSize":32,"dataType":32,"dataTypeSequence":103,"globalSequence":166,"info":0,"systemTick":38213,"timestamp":{"seconds":634555014},"user1":49,"user2":19},"PacketGenTime":1586449040822,"PacketRxUnixTime":1586449040893,"Bands":[13939,4765,0,0,6295,0,0,0],"ExternalValuesMask":0,"FftSize":3,"IsPowerChannelOverrange":false,"SampleRate":1,"ValidDataMask":19},{"Header":{"dataSize":32,"dataType":32,"dataTypeSequence":104,"globalSequence":170,"info":0,"systemTick":39265,"timestamp":{"seconds":634555014},"user1":49,"user2":19},"PacketGenTime":1586449040927,"PacketRxUnixTime":1586449040948,"Bands":[15246,5842,0,0,6713,0,0,0],"ExternalValuesMask":0,"FftSize":3,"IsPowerChannelOverrange":false,"SampleRate":1,"ValidDataMask":19},{"Header":{"dataSize":32,"dataType":32,"dataTypeSequence":105,"globalSequence":173,"info":0,"systemTick":40233,"timestamp":{"seconds":634555014},"user1":49,"user2":19},"PacketGenTime":1586449041024,"PacketRxUnixTime":1586449040995,"Bands":[15475,6627,0,0,7387,0,0,0],"ExternalValuesMask":0,"FftSize":3,"IsPowerChannelOverrange":false,"SampleRate":1,"ValidDataMask":19},{"Header":{"dataSize":32,"dataType":32,"dataTypeSequence":106,"globalSequence":177,"info":0,"systemTick":41196,"timestamp":{"seconds":634555015},"user1":49,"user2":19},"PacketGenTime":1586449041120,"PacketRxUnixTime":1586449041114,"Bands":[13887,6610,0,0,8181,0,0,0],"ExternalValuesMask":0,"FftSize":3,"IsPowerChannelOverrange":false,"SampleRate":1,"ValidDataMask":19},{"Header":{"dataSize":32,"dataType":32,"dataTypeSequence":107,"globalSequence":182,"info":0,"systemTick":42200,"timestamp":{"seconds":634555015},"user1":49,"user2":19},"PacketGenTime":1586449041183,"PacketRxUnixTime":1586449041247,"Bands":[11789,6649,0,0,8608,0,0,0],"ExternalValuesMask":0,"FftSize":3,"IsPowerChannelOverrange":false,"SampleRate":1,"ValidDataMask":19},{"Header":{"dataSize":32,"dataType":32,"dataTypeSequence":108,"globalSequence":187,"info":0,"systemTick":43387,"timestamp":{"seconds":634555015},"user1":49,"user2":19},"PacketGenTime":1586449041301,"PacketRxUnixTime":1586449041367,"Bands":[8968,5838,0,0,8773,0,0,0],"ExternalValuesMask":0,"FftSize":3,"IsPowerChannelOverrange":false,"SampleRate":1,"ValidDataMask":19},{"Header":{"dataSize":32,"dataType":32,"dataTypeSequence":109,"globalSequence":190,"info":0,"systemTick":44249,"timestamp":{"seconds":634555015},"user1":49,"user2":19},"PacketGenTime":1586449041388,"PacketRxUnixTime":1586449041430,"Bands":[6376,5044,0,0,8408,0,0,0],"ExternalValuesMask":0,"FftSize":3,"IsPowerChannelOverrange":false,"SampleRate":1,"ValidDataMask":19},{"Header":{"dataSize":32,"dataType":32,"dataTypeSequence":110,"globalSequence":193,"info":0,"systemTick":45217,"timestamp":{"seconds":634555015},"user1":49,"user2":19},"PacketGenTime":1586449041484,"PacketRxUnixTime":1586449041587,"Bands":[4271,4032,0,0,7745,0,0,0],"ExternalValuesMask":0,"FftSize":3,"IsPowerChannelOverrange":false,"SampleRate":1,"ValidDataMask":19},{"Header":{"dataSize":32,"dataType":32,"dataTypeSequence":111,"globalSequence":198,"info":0,"systemTick":46387,"timestamp":{"seconds":634555015},"user1":49,"user2":19},"PacketGenTime":1586449041601,"PacketRxUnixTime":1586449041659,"Bands":[2816,3145,0,0,7323,0,0,0],"ExternalValuesMask":0,"FftSize":3,"IsPowerChannelOverrange":false,"SampleRate":1,"ValidDataMask":19},{"Header":{"dataSize":32,"dataType":32,"dataTypeSequence":112,"globalSequence":201,"info":0,"systemTick":47223,"timestamp":{"seconds":634555015},"user1":49,"user2":19},"PacketGenTime":1586449041685,"PacketRxUnixTime":1586449041719,"Bands":[2177,2555,0,0,6574,0,0,0],"ExternalValuesMask":0,"FftSize":3,"IsPowerChannelOverrange":false,"SampleRate":1,"ValidDataMask":19},{"Header":{"dataSize":32,"dataType":32,"dataTypeSequence":113,"globalSequence":205,"info":0,"systemTick":48234,"timestamp":{"seconds":634555015},"user1":49,"user2":19},"PacketGenTime":1586449041786,"PacketRxUnixTime":1586449041793,"Bands":[2322,2428,0,0,6299,0,0,0],"ExternalValuesMask":0,"FftSize":3,"IsPowerChannelOverrange":false,"SampleRate":1,"ValidDataMask":19},{"Header":{"dataSize":32,"dataType":32,"dataTypeSequence":114,"globalSequence":209,"info":0,"systemTick":49230,"timestamp":{"seconds":634555015},"user1":49,"user2":19},"PacketGenTime":1586449041886,"PacketRxUnixTime":1586449041954,"Bands":[2545,2438,0,0,6279,0,0,0],"ExternalValuesMask":0,"FftSize":3,"IsPowerChannelOverrange":false,"SampleRate":1,"ValidDataMask":19},{"Header":{"dataSize":32,"dataType":32,"dataTypeSequence":115,"globalSequence":213,"info":0,"systemTick":50149,"timestamp":{"seconds":634555015},"user1":49,"user2":19},"PacketGenTime":1586449041978,"PacketRxUnixTime":1586449042023,"Bands":[3067,2866,0,0,6398,0,0,0],"ExternalValuesMask":0,"FftSize":3,"IsPowerChannelOverrange":false,"SampleRate":1,"ValidDataMask":19},{"Header":{"dataSize":32,"dataType":32,"dataTypeSequence":116,"globalSequence":216,"info":0,"systemTick":51160,"timestamp":{"seconds":634555016},"user1":49,"user2":19},"PacketGenTime":1586449042079,"PacketRxUnixTime":1586449042085,"Bands":[3253,3285,0,0,6378,0,0,0],"ExternalValuesMask":0,"FftSize":3,"IsPowerChannelOverrange":false,"SampleRate":1,"ValidDataMask":19},{"Header":{"dataSize":32,"dataType":32,"dataTypeSequence":117,"globalSequence":221,"info":0,"systemTick":52205,"timestamp":{"seconds":634555016},"user1":49,"user2":19},"PacketGenTime":1586449042208,"PacketRxUnixTime":1586449042253,"Bands":[3121,3645,0,0,6026,0,0,0],"ExternalValuesMask":0,"FftSize":3,"IsPowerChannelOverrange":false,"SampleRate":1,"ValidDataMask":19},{"Header":{"dataSize":32,"dataType":32,"dataTypeSequence":118,"globalSequence":225,"info":0,"systemTick":53221,"timestamp":{"seconds":634555016},"user1":49,"user2":19},"PacketGenTime":1586449042309,"PacketRxUnixTime":1586449042368,"Bands":[2655,4091,0,0,5470,0,0,0],"ExternalValuesMask":0,"FftSize":3,"IsPowerChannelOverrange":false,"SampleRate":1,"ValidDataMask":19},{"Header":{"dataSize":32,"dataType":32,"dataTypeSequence":119,"globalSequence":230,"info":0,"systemTick":54387,"timestamp":{"seconds":634555016},"user1":49,"user2":19},"PacketGenTime":1586449042426,"PacketRxUnixTime":1586449042450,"Bands":[2474,4309,0,0,4811,0,0,0],"ExternalValuesMask":0,"FftSize":3,"IsPowerChannelOverrange":false,"SampleRate":1,"ValidDataMask":19},{"Header":{"dataSize":32,"dataType":32,"dataTypeSequence":120,"globalSequence":233,"info":0,"systemTick":55270,"timestamp":{"seconds":634555016},"user1":49,"user2":19},"PacketGenTime":1586449042514,"PacketRxUnixTime":1586449042683,"Bands":[2089,4309,0,0,4145,0,0,0],"ExternalValuesMask":0,"FftSize":3,"IsPowerChannelOverrange":false,"SampleRate":1,"ValidDataMask":19},{"Header":{"dataSize":32,"dataType":32,"dataTypeSequence":121,"globalSequence":236,"info":0,"systemTick":56239,"timestamp":{"seconds":634555016},"user1":49,"user2":19},"PacketGenTime":1586449042611,"PacketRxUnixTime":1586449042693,"Bands":[1824,3970,0,0,3703,0,0,0],"ExternalValuesMask":0,"FftSize":3,"IsPowerChannelOverrange":false,"SampleRate":1,"ValidDataMask":19},{"Header":{"dataSize":32,"dataType":32,"dataTypeSequence":122,"globalSequence":240,"info":0,"systemTick":57188,"timestamp":{"seconds":634555016},"user1":49,"user2":19},"PacketGenTime":1586449042706,"PacketRxUnixTime":1586449042730,"Bands":[1589,3657,0,0,3733,0,0,0],"ExternalValuesMask":0,"FftSize":3,"IsPowerChannelOverrange":false,"SampleRate":1,"ValidDataMask":19},{"Header":{"dataSize":32,"dataType":32,"dataTypeSequence":123,"globalSequence":244,"info":0,"systemTick":58205,"timestamp":{"seconds":634555016},"user1":49,"user2":19},"PacketGenTime":1586449042808,"PacketRxUnixTime":1586449042810,"Bands":[1577,3316,0,0,3701,0,0,0],"ExternalValuesMask":0,"FftSize":3,"IsPowerChannelOverrange":false,"SampleRate":1,"ValidDataMask":19},{"Header":{"dataSize":32,"dataType":32,"dataTypeSequence":124,"globalSequence":249,"info":0,"systemTick":59381,"timestamp":{"seconds":634555016},"user1":49,"user2":19},"PacketGenTime":1586449042925,"PacketRxUnixTime":1586449043042,"Bands":[1713,3159,0,0,4121,0,0,0],"ExternalValuesMask":0,"FftSize":3,"IsPowerChannelOverrange":false,"SampleRate":1,"ValidDataMask":19},{"Header":{"dataSize":32,"dataType":32,"dataTypeSequence":125,"globalSequence":252,"info":0,"systemTick":60251,"timestamp":{"seconds":634555016},"user1":49,"user2":19},"PacketGenTime":1586449043012,"PacketRxUnixTime":1586449043046,"Bands":[1856,3217,0,0,4542,0,0,0],"ExternalValuesMask":0,"FftSize":3,"IsPowerChannelOverrange":false,"SampleRate":1,"ValidDataMask":19},{"Header":{"dataSize":32,"dataType":32,"dataTypeSequence":126,"globalSequence":0,"info":0,"systemTick":61183,"timestamp":{"seconds":634555017},"user1":49,"user2":19},"PacketGenTime":1586449043106,"PacketRxUnixTime":1586449043207,"Bands":[2181,3352,0,0,5446,0,0,0],"ExternalValuesMask":0,"FftSize":3,"IsPowerChannelOverrange":false,"SampleRate":1,"ValidDataMask":19},{"Header":{"dataSize":32,"dataType":32,"dataTypeSequence":127,"globalSequence":4,"info":0,"systemTick":62197,"timestamp":{"seconds":634555017},"user1":49,"user2":19},"PacketGenTime":1586449043273,"PacketRxUnixTime":1586449043213,"Bands":[2400,3516,0,0,6374,0,0,0],"ExternalValuesMask":0,"FftSize":3,"IsPowerChannelOverrange":false,"SampleRate":1,"ValidDataMask":19},{"Header":{"dataSize":32,"dataType":32,"dataTypeSequence":128,"globalSequence":9,"info":0,"systemTick":63384,"timestamp":{"seconds":634555017},"user1":49,"user2":19},"PacketGenTime":1586449043392,"PacketRxUnixTime":1586449043338,"Bands":[2502,3842,0,0,7655,0,0,0],"ExternalValuesMask":0,"FftSize":3,"IsPowerChannelOverrange":false,"SampleRate":1,"ValidDataMask":19},{"Header":{"dataSize":32,"dataType":32,"dataTypeSequence":129,"globalSequence":12,"info":0,"systemTick":64259,"timestamp":{"seconds":634555017},"user1":49,"user2":19},"PacketGenTime":1586449043479,"PacketRxUnixTime":1586449043446,"Bands":[2338,4287,0,0,9166,0,0,0],"ExternalValuesMask":0,"FftSize":3,"IsPowerChannelOverrange":false,"SampleRate":1,"ValidDataMask":19},{"Header":{"dataSize":32,"dataType":32,"dataTypeSequence":130,"globalSequence":16,"info":0,"systemTick":65237,"timestamp":{"seconds":634555017},"user1":49,"user2":19},"PacketGenTime":1586449043577,"PacketRxUnixTime":1586449043522,"Bands":[2119,4470,0,0,10797,0,0,0],"ExternalValuesMask":0,"FftSize":3,"IsPowerChannelOverrange":false,"SampleRate":1,"ValidDataMask":19},{"Header":{"dataSize":32,"dataType":32,"dataTypeSequence":131,"globalSequence":20,"info":0,"systemTick":770,"timestamp":{"seconds":634555017},"user1":49,"user2":19},"PacketGenTime":1586449043684,"PacketRxUnixTime":1586449043590,"Bands":[1777,4685,0,0,12791,0,0,0],"ExternalValuesMask":0,"FftSize":3,"IsPowerChannelOverrange":false,"SampleRate":1,"ValidDataMask":19}]}]